yyp/__init__.py
yyp/__main__.py
yyp/auto_build.py
yyp/makefile_modifier.py
yyp-0.2.2.dist-info/licenses/LICENSE
yyp-0.2.2.dist-info/METADATA
yyp-0.2.2.dist-info/WHEEL
yyp-0.2.2.dist-info/entry_points.txt
yyp-0.2.2.dist-info/top_level.txt
yyp-0.2.2.dist-info/RECORD
